blackscholes/__init__.py
blackscholes/base.py
blackscholes/butterfly.py
blackscholes/call.py
blackscholes/iron_butterfly.py
blackscholes/iron_condor.py
blackscholes/put.py
blackscholes/spread.py
blackscholes/straddle.py
blackscholes/strangle.py
blackscholes/tests/__init__.py
blackscholes/tests/test_base.py
blackscholes/tests/test_butterfly.py
blackscholes/tests/test_call.py
blackscholes/tests/test_iron_butterfly.py
blackscholes/tests/test_iron_condor.py
blackscholes/tests/test_put.py
blackscholes/tests/test_spread.py
blackscholes/tests/test_straddle.py
blackscholes/tests/test_strangle.py
blackscholes-0.1.8.dist-info/LICENSE
blackscholes-0.1.8.dist-info/METADATA
blackscholes-0.1.8.dist-info/WHEEL
blackscholes-0.1.8.dist-info/RECORD
