Metadata-Version: 2.1
Name: blackscholes
Version: 0.1.8
Summary: Black Scholes calculator for Python including all Greeks
License: MIT
Author: CarloLepelaars
Author-email: info@carlolepelaars.nl
Requires-Python: >=3.8.1,<4.0.0
Classifier: License :: OSI Approved :: MIT License
Classifier: Programming Language :: Python :: 3
Classifier: Programming Language :: Python :: 3.9
Classifier: Programming Language :: Python :: 3.10
Classifier: Programming Language :: Python :: 3.11
